tdbear/__init__.py
tdbear/_util/__init__.py
tdbear/_util/console.py
tdbear/_util/typevars.py
tdbear/analyzer/__init__.py
tdbear/analyzer/module_funcs.py
tdbear/analyzer/analysis_model/__init__.py
tdbear/analyzer/analysis_model/analysis_model.py
tdbear/analyzer/analysis_result/__init__.py
tdbear/analyzer/analysis_result/analysis_result.py
tdbear/analyzer/curves/__init__.py
tdbear/analyzer/curves/curve.py
tdbear/analyzer/curves/tds_container.py
tdbear/analyzer/curves/tds_curve.py
tdbear/analyzer/dataset/__init__.py
tdbear/analyzer/dataset/module_funcs.py
tdbear/analyzer/dataset/nanakoberry.yml
tdbear/analyzer/hcluster/__init__.py
tdbear/analyzer/hcluster/hcluster.py
tdbear/analyzer/labels/__init__.py
tdbear/analyzer/labels/labels.py
tdbear/analyzer/pca/__init__.py
tdbear/analyzer/pca/pca.py
tdbear/analyzer/pca/pca_result.py
tdbear/analyzer/trajectory_plot/__init__.py
tdbear/analyzer/trajectory_plot/trajectory_plot.py
tdbear/analyzer/trajectory_plot/trajectory_plot_result.py
tdbear/sampler/__init__.py
tdbear/sampler/favicon.ico
tdbear/sampler/sampler.py
tdbear/sampler/sampler_options.py
tdbear/sampler/sampler_util.py
tdbear-1.0.11.dist-info/LICENSE.txt
tdbear-1.0.11.dist-info/METADATA
tdbear-1.0.11.dist-info/WHEEL
tdbear-1.0.11.dist-info/top_level.txt
tdbear-1.0.11.dist-info/RECORD
