Metadata-Version: 2.1
Name: tdbear
Version: 1.0.11
Summary: A module assisting with experiments and analysis of TDS methods.
Home-page: https://hci.fpark.tmu.ac.jp/TDbear/
Author: TMU HCI lab.
License: MIT
Project-URL: Documentation, https://hci.fpark.tmu.ac.jp/TDbear/
Project-URL: Source, https://github.com/tmu-hci/TDbear
Keywords: TDS TDbear
Classifier: Programming Language :: Python :: 3
Classifier: Topic :: Scientific/Engineering :: Information Analysis
Classifier: Topic :: Scientific/Engineering :: Mathematics
Classifier: Topic :: Scientific/Engineering :: Visualization
Classifier: Topic :: Software Development :: User Interfaces
Classifier: Topic :: Software Development :: Libraries :: Python Modules
Classifier: Intended Audience :: Information Technology
Classifier: Intended Audience :: Science/Research
Classifier: License :: OSI Approved :: MIT License
Requires-Python: >=3.11.0
License-File: LICENSE.txt
Requires-Dist: matplotlib
Requires-Dist: numpy
Requires-Dist: scipy
Requires-Dist: PySimpleGUI
Requires-Dist: PyYAML
Requires-Dist: scikit-learn
